setup.py
src/RedisClusterLibrary/RedisClusterLibraryKeywords.py
src/RedisClusterLibrary/__init__.py
src/RedisClusterLibrary.egg-info/PKG-INFO
src/RedisClusterLibrary.egg-info/SOURCES.txt
src/RedisClusterLibrary.egg-info/dependency_links.txt
src/RedisClusterLibrary.egg-info/top_level.txt